{"data":{"site":{"siteMetadata":{"title":"Jess2.xyz","author":"Jess2","siteUrl":"http://jess2.xyz","comment":{"disqusShortName":"https-jess2-netlify-com","utterances":""},"sponsor":{"buyMeACoffeeId":"Jess2"}}},"markdownRemark":null},"pageContext":{"isCreatedByStatefulCreatePages":false,"slug":"/JavaScript/[js]-null과-undefined-비교/","previous":{"fields":{"slug":"/JavaScript/delegation/"},"frontmatter":{"title":"[JS] 이벤트 위임","category":"javascript"}},"next":{"fields":{"slug":"/JavaScript/cross-domain/"},"frontmatter":{"title":"[JS] 크로스 도메인(Cross Domain)","category":"javascript"}}}}