{"data":{"site":{"siteMetadata":{"title":"Jess2.xyz","author":"Jess2","siteUrl":"http://jess2.xyz","comment":{"disqusShortName":"https-jess2-netlify-com","utterances":""},"sponsor":{"buyMeACoffeeId":"Jess2"}}},"markdownRemark":{"id":"aaaa5022-ab42-5753-ad83-618cad57e7a8","excerpt":"","html":"","frontmatter":{"title":"refs","date":"April 01, 2020"}}},"pageContext":{"isCreatedByStatefulCreatePages":false,"slug":"/vue/refs/","previous":{"fields":{"slug":"/vue/component-props/"},"frontmatter":{"title":"[vue.js] 하위 컴포넌트 등록과 Props","category":"vue"}},"next":null}}